MANIFEST.in
README.md
setup.cfg
setup.py
versioneer.py
phylonetwork/__init__.py
phylonetwork/_version.py
phylonetwork/balances.py
phylonetwork/btctc_generators.py
phylonetwork/eNewick.py
phylonetwork/exceptions.py
phylonetwork/tree_generators.py
phylonetwork/tree_operations.py
phylonetwork/tree_shapes.py
phylonetwork/utils.py
phylonetwork.egg-info/PKG-INFO
phylonetwork.egg-info/SOURCES.txt
phylonetwork.egg-info/dependency_links.txt
phylonetwork.egg-info/requires.txt
phylonetwork.egg-info/top_level.txt