Metadata-Version: 2.1
Name: phylonetwork
Version: 2.2.1
Home-page: https://github.com/bielcardona/PhyloNetworks
Author: Gabriel Cardona
Author-email: bielcardona@gmail.com
License: BSD
Keywords: phylogenetic trees networks
Requires-Python: >=3.7
